odoo10_addon_l10n_es_location_nuts-10.0.1.0.0-py2.7-nspkg.pth
odoo/addons/l10n_es_location_nuts/README.rst
odoo/addons/l10n_es_location_nuts/__init__.py
odoo/addons/l10n_es_location_nuts/__manifest__.py
odoo/addons/l10n_es_location_nuts/hooks.py
odoo/addons/l10n_es_location_nuts/i18n/es.po
odoo/addons/l10n_es_location_nuts/static/description/icon.png
odoo/addons/l10n_es_location_nuts/wizard/__init__.py
odoo/addons/l10n_es_location_nuts/wizard/nuts_import.py
odoo10_addon_l10n_es_location_nuts-10.0.1.0.0.dist-info/DESCRIPTION.rst
odoo10_addon_l10n_es_location_nuts-10.0.1.0.0.dist-info/METADATA
odoo10_addon_l10n_es_location_nuts-10.0.1.0.0.dist-info/RECORD
odoo10_addon_l10n_es_location_nuts-10.0.1.0.0.dist-info/WHEEL
odoo10_addon_l10n_es_location_nuts-10.0.1.0.0.dist-info/metadata.json
odoo10_addon_l10n_es_location_nuts-10.0.1.0.0.dist-info/namespace_packages.txt
odoo10_addon_l10n_es_location_nuts-10.0.1.0.0.dist-info/top_level.txt
